grandeur-0.1.4-py3.7-nspkg.pth
grandeur/device/__init__.py
grandeur/device/handlers/__init__.py
grandeur/device/handlers/duplex.py
grandeur/device/src/__init__.py
grandeur/device/src/device.py
grandeur-0.1.4.dist-info/LICENSE
grandeur-0.1.4.dist-info/METADATA
grandeur-0.1.4.dist-info/WHEEL
grandeur-0.1.4.dist-info/namespace_packages.txt
grandeur-0.1.4.dist-info/top_level.txt
grandeur-0.1.4.dist-info/RECORD
