Metadata-Version: 2.1
Name: grandeur
Version: 0.1.4
Summary: This SDK has been designed to enable developers integrate Grandeur into SOCs with Python
Home-page: https://github.com/grandeurtech/py-sdk
Author: Grandeur Technologies
Author-email: hi@grandeur.tech
License: MIT
Platform: Posix; MacOS X; Windows
Classifier: Development Status :: 3 - Alpha
Classifier: Intended Audience :: Developers
Classifier: License :: OSI Approved :: MIT License
Classifier: Programming Language :: Python
Classifier: Programming Language :: Python :: 3
Classifier: Programming Language :: Python :: 3.6
Classifier: Programming Language :: Python :: 3.7
Classifier: Programming Language :: Python :: 3.8
Classifier: Operating System :: OS Independent
Classifier: Topic :: Internet
Requires-Python: >=3.6
Requires-Dist: websocket-client
Requires-Dist: pyee
